byted_ttcu_mmfinetune/__init__.py
byted_ttcu_mmfinetune-0.0.1.dist-info/METADATA
byted_ttcu_mmfinetune-0.0.1.dist-info/WHEEL
byted_ttcu_mmfinetune-0.0.1.dist-info/top_level.txt
byted_ttcu_mmfinetune-0.0.1.dist-info/RECORD
